LICENCE
yubival/__init__.py
yubival/admin.py
yubival/apps.py
yubival/management/__init__.py
yubival/management/commands/__init__.py
yubival/management/commands/apikey.py
yubival/management/commands/yubikey.py
yubival/migrations/0001_initial.py
yubival/migrations/0002_add_label_and_date_created_fields.py
yubival/migrations/0003_read_only_counters.py
yubival/migrations/__init__.py
yubival/models.py
yubival/urls.py
yubival/validators.py
yubival/views.py
yubival-0.2.0.dist-info/WHEEL
yubival-0.2.0.dist-info/METADATA
yubival-0.2.0.dist-info/RECORD
