Metadata-Version: 2.1
Name: yubival
Version: 0.2.0
Summary: Django app that runs a standalone Yubikey validation server
Home-page: https://github.com/bruot/yubival
License: GPL-3.0-or-later
Author: Nicolas Bruot
Author-email: coremeltdown@bruot.org
Requires-Python: >=3.6,<4.0
Classifier: Development Status :: 4 - Beta
Classifier: Framework :: Django
Classifier: Intended Audience :: Developers
Classifier: License :: OSI Approved :: GNU General Public License v3 or later (GPLv3+)
Classifier: Operating System :: OS Independent
Classifier: Programming Language :: Python
Classifier: Programming Language :: Python :: 3
Classifier: Programming Language :: Python :: 3.10
Classifier: Programming Language :: Python :: 3.6
Classifier: Programming Language :: Python :: 3.7
Classifier: Programming Language :: Python :: 3.8
Classifier: Programming Language :: Python :: 3.9
Classifier: Topic :: Security
Requires-Dist: Django (>=2.2,<4.1)
Requires-Dist: YubiOTP (>=1.0.0,<2.0.0)
Project-URL: Repository, https://github.com/bruot/yubival
